tb_query/__init__.py
tb_query/_version.py
tb_query/cli.py
tb_query/core.py
tb_query/mcp.py
tb_query-2025.11.5.dist-info/licenses/LICENSE
tb_query-2025.11.5.dist-info/METADATA
tb_query-2025.11.5.dist-info/WHEEL
tb_query-2025.11.5.dist-info/entry_points.txt
tb_query-2025.11.5.dist-info/top_level.txt
tb_query-2025.11.5.dist-info/RECORD
