Metadata-Version: 2.4
Name: tb-query
Version: 2025.11.5
Summary: A CLI tool and MCP (Model Context Protocol) server for querying and analyzing TensorBoard event files without requiring a running TensorBoard server.
Author-email: Alireza Savand <alireza.savand@gmail.com>
License-Expression: GPL-3.0-or-later
Project-URL: Homepage, https://github.com/Alir3z4/tb-query
Project-URL: Repository, https://github.com/Alir3z4/tb-query.git
Project-URL: Issues, https://github.com/Alir3z4/tb-query/issues
Project-URL: Changelog, https://github.com/Alir3z4/tb-query/blob/master/ChangeLog.md
Classifier: Development Status :: 5 - Production/Stable
Classifier: Intended Audience :: Developers
Classifier: Intended Audience :: Science/Research
Classifier: Operating System :: OS Independent
Classifier: Programming Language :: Python
Classifier: Programming Language :: Python :: 3
Classifier: Programming Language :: Python :: 3.11
Classifier: Programming Language :: Python :: 3.12
Classifier: Programming Language :: Python :: 3.13
Classifier: Programming Language :: Python :: 3 :: Only
Classifier: Topic :: Scientific/Engineering
Classifier: Topic :: Scientific/Engineering :: Artificial Intelligence
Classifier: Topic :: Scientific/Engineering :: Information Analysis
Classifier: Topic :: Scientific/Engineering :: Visualization
Classifier: Topic :: Software Development
Classifier: Topic :: Software Development :: Libraries
Classifier: Topic :: Software Development :: Libraries :: Python Modules
Classifier: Topic :: System :: Monitoring
Classifier: Topic :: Utilities
Classifier: Typing :: Typed
Classifier: Environment :: Console
Requires-Python: >=3.11
License-File: LICENSE
Requires-Dist: tensorboard==2.20.0
Requires-Dist: fastmcp==2.13.0.2
Requires-Dist: pandas==2.3.3
Provides-Extra: dev
Requires-Dist: black==25.9.0; extra == "dev"
Requires-Dist: mypy==1.18.2; extra == "dev"
Requires-Dist: flake8==7.3.0; extra == "dev"
Requires-Dist: isort==7.0.0; extra == "dev"
Requires-Dist: coverage==7.11.0; extra == "dev"
Dynamic: license-file
